setup.cfg
setup.py
rino/__init__.py
rino/browse.py
rino/cli.py
rino/config.py
rino/git_tools.py
rino/initialize.py
rino/login.py
rino/notebook.py
rino/remote.py
rino/utils.py
rino.egg-info/PKG-INFO
rino.egg-info/SOURCES.txt
rino.egg-info/dependency_links.txt
rino.egg-info/entry_points.txt
rino.egg-info/requires.txt
rino.egg-info/top_level.txt