Metadata-Version: 1.0
Name: rino
Version: 0.0.6
Summary: Rinocloud CLI tool
Home-page: UNKNOWN
Author: Eoin Murray
Author-email: eoin@rinocloud.com
License: UNKNOWN
Platform: UNKNOWN
